llmUnify/__init__.py
llmUnify/_abstract_connector.py
llmUnify/_connector_factory.py
llmUnify/_options.py
llmUnify/_response.py
llmUnify/_usage_metrics_logger.py
llmUnify/providers/aws/__init__.py
llmUnify/providers/aws/_connector.py
llmUnify/providers/aws/_options.py
llmUnify/providers/aws/_response.py
llmUnify/providers/azure/__init__.py
llmUnify/providers/azure/_connector.py
llmUnify/providers/azure/_options.py
llmUnify/providers/azure/_response.py
llmUnify/providers/google/__init__.py
llmUnify/providers/google/_connector.py
llmUnify/providers/google/_options.py
llmUnify/providers/google/_response.py
llmUnify/providers/ollama/__init__.py
llmUnify/providers/ollama/_connector.py
llmUnify/providers/ollama/_options.py
llmUnify/providers/ollama/_response.py
llmUnify/providers/watsonx/__init__.py
llmUnify/providers/watsonx/_connector.py
llmUnify/providers/watsonx/_options.py
llmUnify/providers/watsonx/_response.py
llmUnify/utils/_get_env.py
llmunify-1.0.1.dist-info/METADATA
llmunify-1.0.1.dist-info/WHEEL
llmunify-1.0.1.dist-info/RECORD
