Metadata-Version: 2.3
Name: llmUnify
Version: 1.0.1
Summary: LlmUnify is a library that abstracts connections to major LLM model providers, simplifying their invocation and interoperability.
Author: Sistemi Informativi S.r.l.
Requires-Python: >=3.10,<4.0
Classifier: Programming Language :: Python :: 3
Classifier: Programming Language :: Python :: 3.10
Classifier: Programming Language :: Python :: 3.11
Classifier: Programming Language :: Python :: 3.12
Classifier: Programming Language :: Python :: 3.13
Provides-Extra: all
Provides-Extra: aws
Provides-Extra: azure
Provides-Extra: google
Provides-Extra: ollama
Provides-Extra: watsonx
Requires-Dist: azure-ai-inference (>=1.0.0b9,<2.0.0) ; extra == "azure" or extra == "all"
Requires-Dist: boto3 (>=1.36.2,<2.0.0) ; extra == "aws" or extra == "all"
Requires-Dist: ibm-watsonx-ai (>=1.1.16,<2.0.0) ; extra == "watsonx" or extra == "all"
Requires-Dist: pydantic (>=2.10.5,<3.0.0)
Requires-Dist: requests (>=2.32.3,<3.0.0) ; extra == "ollama" or extra == "all"
Requires-Dist: vertexai (>=1.71.1,<2.0.0) ; extra == "google" or extra == "all"
